errorhub/__init__.py
errorhub/decorator.py
errorhub/exceptions.py
errorhub/helper.py
errorhub/models.py
errorhub-0.1.8.dist-info/METADATA
errorhub-0.1.8.dist-info/WHEEL
errorhub-0.1.8.dist-info/top_level.txt
errorhub-0.1.8.dist-info/RECORD
