Metadata-Version: 2.4
Name: errorhub
Version: 0.1.8
Summary: Error and Exception Handling lib
Home-page: https://github.com/unfettered-one/Error-Hub.git
Author: Yash Pakhale
Author-email: pakhaleyash7@gmail.com
Requires-Dist: fastapi==0.116.1
Requires-Dist: pydantic==2.11.7
Requires-Dist: dotenv==0.9.9
Requires-Dist: requests==2.32.5
Dynamic: author
Dynamic: author-email
Dynamic: home-page
Dynamic: requires-dist
Dynamic: summary
